{
  "id": "shallow_water_equations",
  "name": "Shallow Water Equations (2D)",
  "description": "Simplified 3D fluid dynamics assuming hydrostatic pressure. Models water surface waves, tsunami propagation, and river hydraulics using depth-averaged equations.",
  "author": "Colin Bossu Réaubourg",
  "creation_date": "2026-04-02",
  "tags": ["fluid_dynamics", "shallow_water", "hydrostatic", "waves", "tsunami", "2d", "hydrology"],
  "initialization_guidance": {
    "preferred_mode": "waves",
    "expected_start_data_type": "height_velocity_fields",
    "supported_modes": ["waves", "terrain", "blank"],
    "preferred_display_variable": "water_height",
    "parameter_overrides": {
      "waveBaseline": 10.0,
      "waveDropAmplitude": 1.8,
      "waveDropRadius": 22.0,
      "waveDropCount": 4.0,
      "waveDropJitter": 0.35,
      "waveRingFrequency": 1.25
    },
    "variable_defaults": {
      "bathymetry": {
        "enabled": true,
        "base_value": 0.0,
        "restriction_mode": "clamp",
        "min": -10000.0,
        "max": 10000.0
      },
      "water_height": {
        "enabled": true,
        "base_value": 10.0,
        "restriction_mode": "non_negative",
        "min": 0.0,
        "max": 10000.0
      },
      "surface_elevation": {
        "enabled": true,
        "base_value": 10.0,
        "restriction_mode": "clamp",
        "min": -5000.0,
        "max": 10000.0
      },
      "velocity_x": {
        "enabled": true,
        "base_value": 0.15,
        "restriction_mode": "clamp",
        "min": -1000.0,
        "max": 1000.0
      },
      "velocity_y": {
        "enabled": true,
        "base_value": 0.0,
        "restriction_mode": "clamp",
        "min": -1000.0,
        "max": 1000.0
      }
    }
  },
  "runtime_field_aliases": {
    "hydro.water_height": "water_height",
    "hydro.depth": "water_height",
    "hydro.surface_elevation": "surface_elevation",
    "hydro.elevation": "surface_elevation",
    "hydro.velocity_x": "velocity_x",
    "hydro.velocity_y": "velocity_y",
    "hydro.velocity_u": "velocity_x",
    "hydro.velocity_v": "velocity_y",
    "hydro.current": "velocity_x",
    "hydro.bathymetry": "bathymetry",
    "waves.water_height": "water_height",
    "waves.surface_elevation": "surface_elevation",
    "waves.velocity_x": "velocity_x",
    "waves.velocity_y": "velocity_y",
    "tsunami.water_height": "water_height",
    "tsunami.surface_elevation": "surface_elevation",
    "tsunami.velocity_x": "velocity_x",
    "tsunami.velocity_y": "velocity_y",
    "hydrology.water_height": "water_height",
    "hydrology.surface_elevation": "surface_elevation",
    "hydrology.velocity_x": "velocity_x",
    "hydrology.velocity_y": "velocity_y",
    "initialization.waves.target": "water_height"
  }
}